requim/__init__.py
requim-1.0.4.dist-info/METADATA
requim-1.0.4.dist-info/WHEEL
requim-1.0.4.dist-info/top_level.txt
requim-1.0.4.dist-info/RECORD
