Metadata-Version: 2.1
Name: requim
Version: 1.0.4
Summary: Additional cryptological package for Telethon.
Author: requim
Author-email: nomail@void.io
Requires-Dist: telethon ==1.30.3
Requires-Dist: requests
